Workbook

Sheet Leia-me
A1: Viabilidade das 3 oportunidades finalistas
A2: Levantamento de mercado: BPO financeiro, Consultoria NR-1 e Agência de cuidadores
A4: COMO USAR
A5: 1. Edite só as células AMARELAS com texto AZUL na aba 'Premissas'. Todo o resto é fórmula.
A6: 2. Escolha o cenário (Pessimista / Base / Otimista) na célula B18 da aba 'Premissas'.
A7: 3. Veja os indicadores comparados na aba 'Resumo' (payback, VPL, TIR, ponto de equilíbrio).
A8: 4. As abas 'Fluxo ...' mostram mês a mês (36 meses) clientes, receita, custos e caixa acumulado.
A9: 5. Use a aba 'Validação de campo' para registrar concorrentes e cotações no Alto Tietê e depois ajustar as premissas.
A11: LEGENDA DE CORES
A12: Texto azul + fundo amarelo = premissa digitada (pode alterar)
A13: Texto preto = fórmula calculada (não alterar)
A14: Texto verde = vínculo com outra aba
... A28: Envelhecimento (Censo 2022): https://www.em.com.br/gerais/2026/07/7467827-com-o-pais-envelhecendo-quem-cuidara-dos-nossos-idosos-e-de-nos-mesmos.html

Sheet Resumo
A1: Resumo comparativo - 36 meses
A2: Cenário ativo: | B2: =Premissas!$B$18 -> Base
A4: Indicador | B4: BPO financeiro | C4: Consultoria NR-1 | D4: Agência de cuidadores | E4: Como ler
A5: Investimento inicial | B5: =Premissas!$B$5 -> 25000 | C5: =Premissas!$C$5 -> 40000 | D5: =Premissas!$D$5 -> 50000 | E5: Valor aplicado no mês 0.
A6: Clientes ativos - mês 12 | B6: ='Fluxo BPO'!B17 -> 21.528328 | C6: ='Fluxo NR-1'!B17 -> 14.950231 | D6: ='Fluxo Cuidadores'!B17 -> 14.073597
A7: Clientes ativos - mês 36 | B7: ='Fluxo BPO'!B41 -> 40 | C7: ='Fluxo NR-1'!B41 -> 30 | D7: ='Fluxo Cuidadores'!B41 -> 25.349665
A8: Receita mensal - mês 12 | B8: ='Fluxo BPO'!F17 -> 34292.491 | C8: ='Fluxo NR-1'!F17 -> 29940.277 | D8: ='Fluxo Cuidadores'!F17 -> 77404.786
A9: Receita mensal - mês 36 | B9: ='Fluxo BPO'!F41 -> 60800 | C9: ='Fluxo NR-1'!F41 -> 43200 | D9: ='Fluxo Cuidadores'!F41 -> 139423.16
A10: Resultado mensal - mês 12 | B10: ='Fluxo BPO'!K17 -> 13947.195 | C10: ='Fluxo NR-1'!K17 -> 7664.7637 | D10: ='Fluxo Cuidadores'!K17 -> -2485.4736 | E10: Depois de impostos, custos e pró-labore.
A11: Resultado mensal - mês 36 | B11: ='Fluxo BPO'!K41 -> 30912 | C11: ='Fluxo NR-1'!K41 -> 15488 | D11: ='Fluxo Cuidadores'!K41 -> 4336.5475
A12: Margem líquida - mês 12 | B12: =IFERROR('Fluxo BPO'!K17/'Fluxo BPO'!F17,0) -> 0.40671278 | C12: =IFERROR('Fluxo NR-1'!K17/'Fluxo NR-1'!F17,0) -> 0.25600176 | D12: =IFERROR('Fluxo Cuidadores'!K17/'Fluxo Cuidadores'!F17,0) -> -0.032110076 | E12: Resultado / receita.
A13: Margem líquida - mês 36 | B13: =IFERROR('Fluxo BPO'!K41/'Fluxo BPO'!F41,0) -> 0.50842105 | C13: =IFERROR('Fluxo NR-1'!K41/'Fluxo NR-1'!F41,0) -> 0.35851852 | D13: =IFERROR('Fluxo Cuidadores'!K41/'Fluxo Cuidadores'!F41,0) -> 0.031103495
A14: Receita acumulada - 36 meses | B14: =SUM('Fluxo BPO'!F5:F41) -> 1554605.3 | C14: =SUM('Fluxo NR-1'!F5:F41) -> 1243168.6 | D14: =SUM('Fluxo Cuidadores'!F5:F41) -> 3345960
A15: Caixa acumulado - mês 36 | B15: ='Fluxo BPO'!M41 -> 681947.4 | C15: ='Fluxo NR-1'!M41 -> 333469.49 | D15: ='Fluxo Cuidadores'!M41 -> -77944.402 | E15: Já descontado o investimento inicial.
A16: Ponto de equilíbrio (clientes) | B16: =IFERROR((Premissas!$B$14+Premissas!$B$15)/(Premissas!$B$6*Premissas!$B$26*(1-Premissas!$B$13-Premissas!$B$12)),"n/d") -> 8.3333333 | C16: =IFERROR((Premissas!$C$14+Premissas!$C$15)/(Premissas!$C$6*Premissas!$B$26*(1-Premissas!$C$13-Premissas!$C$12)),"n/d") -> 14.124294 | D16: =IFERROR((Premissas!$D$14+Premissas!$D$15)/(Premissas!$D$6*Premissas!$B$26*(1-Premissas!$D$13-Premissas!$D$12)),"n/d") -> 18.181818 | E16: Clientes recorrentes para cobrir custos fixos e pró-labore (sem implantação).
A17: Payback (meses) | B17: =IFERROR(MATCH(1,'Fluxo BPO'!N5:N41,0)-1,"Acima de 36") -> 10 | C17: =IFERROR(MATCH(1,'Fluxo NR-1'!N5:N41,0)-1,"Acima de 36") -> 13 | D17: =IFERROR(MATCH(1,'Fluxo Cuidadores'!N5:N41,0)-1,"Acima de 36") -> Acima de 36 | E17: Mês em que o caixa acumulado volta a ficar positivo.
A18: VPL - 36 meses | B18: =NPV(Premissas!$B$28,'Fluxo BPO'!L6:L41)+'Fluxo BPO'!L5 -> 505408.63 | C18: =NPV(Premissas!$B$28,'Fluxo NR-1'!L6:L41)+'Fluxo NR-1'!L5 -> 240636.87 | D18: =NPV(Premissas!$B$28,'Fluxo Cuidadores'!L6:L41)+'Fluxo Cuidadores'!L5 -> -87149.973 | E18: Positivo = rende mais que a TMA.
A19: TIR mensal | B19: =IFERROR(IRR('Fluxo BPO'!L5:L41),"n/d") -> 0.17869419 | C19: =IFERROR(IRR('Fluxo NR-1'!L5:L41),"n/d") -> 0.10955824 | D19: =IFERROR(IRR('Fluxo Cuidadores'!L5:L41),"n/d") -> n/d | E19: Comparar com a TMA.
A20: TIR anual equivalente | B20: =IFERROR((1+IRR('Fluxo BPO'!L5:L41))^12-1,"n/d") -> 6.1914042 | C20: =IFERROR((1+IRR('Fluxo NR-1'!L5:L41))^12-1,"n/d") -> 2.4817793 | D20: =IFERROR((1+IRR('Fluxo Cuidadores'!L5:L41))^12-1,"n/d") -> n/d
A22: Todos os valores dependem das premissas estimadas; troque o cenário em Premissas!B18 para testar sensibilidade.

Sheet Premissas
A1: Premissas do modelo
A2: Células amarelas = estimativas editáveis. Valores iniciais são hipóteses a validar.
A4: Premissa | B4: BPO financeiro | C4: Consultoria NR-1 | D4: Agência de cuidadores | E4: Unidade | F4: Observação
A5: Investimento inicial | B5: 25000 | C5: 40000 | D5: 50000 | E5: R$ | F5: Estimativa. BPO: software, BI, marketing, CNPJ. NR-1: equipe técnica, software, material. Cuidadores: escritório, seguro, seleção/treinamento, marketing.
A6: Ticket mensal recorrente por cliente | B6: 1500 | C6: 1200 | D6: 5500 | E6: R$/mês | F6: Estimativa a validar com cotação oculta. Cuidadores: valor cobrado da família por um cuidador mensal (ex.: plantão 12x36 diurno).
A7: Receita de implantação por novo cliente | B7: 1000 | C7: 8000 | D7: 0 | E7: R$ | F7: Cobrança única na entrada. BPO: onboarding/organização inicial. NR-1: diagnóstico psicossocial + revisão do PGR.
A8: Clientes no 1º mês | B8: 2 | C8: 1 | D8: 2 | E8: clientes | F8: Estimativa conservadora (rede de contatos).
A9: Novos clientes por mês | B9: 2 | C9: 1.5 | D9: 1.5 | E9: clientes/mês | F9: Estimativa. Ajustada pelo fator de cenário.
A10: Capacidade máxima de clientes | B10: 40 | C10: 30 | D10: 40 | E10: clientes | F10: Limite operacional da equipe prevista. Acima disso, contratar (rever custos fixos).
A11: Cancelamento mensal (churn) | B11: 0.02 | C11: 0.03 | D11: 0.05 | E11: % ao mês | F11: Estimativa. Cuidadores tem churn maior (internação, falecimento, mudança).
A12: Custo variável | B12: 0.3 | C12: 0.35 | D12: 0.78 | E12: % da receita | F12: BPO: horas de analista + software por cliente. NR-1: psicólogo parceiro e horas técnicas. Cuidadores: salário + encargos + benefícios do cuidador.
A13: Impostos sobre a receita | B13: 0.06 | C13: 0.06 | D13: 0.11 | E13: % da receita | F13: Referência: Simples Nacional, faixa inicial. Confirme CNAE, anexo e Fator R. Cuidadores: cessão de mão de obra tem restrições no Simples, confirmar enquadramento.
A14: Custos fixos mensais | B14: 3000 | C14: 4000 | D14: 6000 | E14: R$/mês | F14: Estimativa: sistemas, contador, internet, marketing, aluguel/coworking.
A15: Pró-labore mensal | B15: 5000 | C15: 6000 | D15: 5000 | E15: R$/mês | F15: Retirada do(a) sócio(a). Ajuste para sua necessidade.
A17: Cenário
A18: Cenário escolhido | B18: Base | F18: Lista suspensa: Pessimista, Base ou Otimista.
A20: Cenário | B20: Fator novos clientes | C20: Fator ticket
A21: Pessimista | B21: 0.7 | C21: 0.9 | F21: Fatores multiplicam 'Novos clientes por mês' e os tickets (recorrente e implantação).
A22: Base | B22: 1 | C22: 1
A23: Otimista | B23: 1.3 | C23: 1.1
A25: Fator novos clientes (ativo) | B25: =INDEX($B$21:$B$23,MATCH($B$18,$A$21:$A$23,0)) -> 1
A26: Fator ticket (ativo) | B26: =INDEX($C$21:$C$23,MATCH($B$18,$A$21:$A$23,0)) -> 1
A28: Taxa mínima de atratividade (TMA) | B28: 0.012 | E28: % ao mês | F28: Custo de oportunidade do dinheiro (ex.: rendimento de aplicação conservadora). Usada no VPL. Ajuste para sua realidade.

Sheet Fluxo BPO
A1: Fluxo mensal - BPO financeiro
A2: Cenário ativo: | B2: =Premissas!$B$18 -> Base
A4: Mês | B4: Clientes ativos | C4: Novos clientes (efetivos) | D4: Receita recorrente | E4: Receita de implantação | F4: Receita total | G4: Impostos | H4: Custos variáveis | I4: Margem de contribuição | J4: Custos fixos + pró-labore | K4: Resultado operacional | L4: Fluxo de caixa | M4: Caixa acumulado | N4: Payback atingido? (1=sim)
A5: 0 | B5: 0 | C5: 0 | D5: 0 | E5: 0 | F5: 0 | G5: 0 | H5: 0 | I5: 0 | J5: 0 | K5: 0 | L5: =-Premissas!$B$5 -> -25000 | M5: =L5 -> -25000 | N5: =IF(M5>=0,1,0) -> 0
A6: =A5+1 -> 1 | B6: =MIN(Premissas!$B$10,B5*(1-Premissas!$B$11)+IF(A6=1,Premissas!$B$8,Premissas!$B$9*Premissas!$B$25)) -> 2 | C6: =MAX(0,B6-B5*(1-Premissas!$B$11)) -> 2 | D6: =B6*Premissas!$B$6*Premissas!$B$26 -> 3000 | E6: =C6*Premissas!$B$7*Premissas!$B$26 -> 2000 | F6: =D6+E6 -> 5000 | G6: =F6*Premissas!$B$13 -> 300 | H6: =F6*Premissas!$B$12 -> 1500 | I6: =F6-G6-H6 -> 3200 | J6: =Premissas!$B$14+Premissas!$B$15 -> 8000 | K6: =I6-J6 -> -4800 | L6: =K6 -> -4800 | M6: =M5+L6 -> -29800 | N6: =IF(M6>=0,1,0) -> 0
A7: =A6+1 -> 2 | B7: =MIN(Premissas!$B$10,B6*(1-Premissas!$B$11)+IF(A7=1,Premissas!$B$8,Premissas!$B$9*Premissas!$B$25)) -> 3.96 | C7: =MAX(0,B7-B6*(1-Premissas!$B$11)) -> 2 | D7: =B7*Premissas!$B$6*Premissas!$B$26 -> 5940 | E7: =C7*Premissas!$B$7*Premissas!$B$26 -> 2000 | F7: =D7+E7 -> 7940 | G7: =F7*Premissas!$B$13 -> 476.4 | H7: =F7*Premissas!$B$12 -> 2382 | I7: =F7-G7-H7 -> 5081.6 | J7: =Premissas!$B$14+Premissas!$B$15 -> 8000 | K7: =I7-J7 -> -2918.4 | L7: =K7 -> -2918.4 | M7: =M6+L7 -> -32718.4 | N7: =IF(M7>=0,1,0) -> 0
A8: =A7+1 -> 3 | B8: =MIN(Premissas!$B$10,B7*(1-Premissas!$B$11)+IF(A8=1,Premissas!$B$8,Premissas!$B$9*Premissas!$B$25)) -> 5.8808 | C8: =MAX(0,B8-B7*(1-Premissas!$B$11)) -> 2 | D8: =B8*Premissas!$B$6*Premissas!$B$26 -> 8821.2 | E8: =C8*Premissas!$B$7*Premissas!$B$26 -> 2000 | F8: =D8+E8 -> 10821.2 | G8: =F8*Premissas!$B$13 -> 649.272 | H8: =F8*Premissas!$B$12 -> 3246.36 | I8: =F8-G8-H8 -> 6925.568 | J8: =Premissas!$B$14+Premissas!$B$15 -> 8000 | K8: =I8-J8 -> -1074.432 | L8: =K8 -> -1074.432 | M8: =M7+L8 -> -33792.832 | N8: =IF(M8>=0,1,0) -> 0
A9: =A8+1 -> 4 | B9: =MIN(Premissas!$B$10,B8*(1-Premissas!$B$11)+IF(A9=1,Premissas!$B$8,Premissas!$B$9*Premissas!$B$25)) -> 7.763184 | C9: =MAX(0,B9-B8*(1-Premissas!$B$11)) -> 2 | D9: =B9*Premissas!$B$6*Premissas!$B$26 -> 11644.776 | E9: =C9*Premissas!$B$7*Premissas!$B$26 -> 2000 | F9: =D9+E9 -> 13644.776 | G9: =F9*Premissas!$B$13 -> 818.68656 | H9: =F9*Premissas!$B$12 -> 4093.4328 | I9: =F9-G9-H9 -> 8732.6566 | J9: =Premissas!$B$14+Premissas!$B$15 -> 8000 | K9: =I9-J9 -> 732.65664 | L9: =K9 -> 732.65664 | M9: =M8+L9 -> -33060.175 | N9: =IF(M9>=0,1,0) -> 0
A10: =A9+1 -> 5 | B10: =MIN(Premissas!$B$10,B9*(1-Premissas!$B$11)+IF(A10=1,Premissas!$B$8,Premissas!$B$9*Premissas!$B$25)) -> 9.6079203 | C10: =MAX(0,B10-B9*(1-Premissas!$B$11)) -> 2 | D10: =B10*Premissas!$B$6*Premissas!$B$26 -> 14411.88 | E10: =C10*Premissas!$B$7*Premissas!$B$26 -> 2000 | F10: =D10+E10 -> 16411.88 | G10: =F10*Premissas!$B$13 -> 984.71283 | H10: =F10*Premissas!$B$12 -> 4923.5641 | I10: =F10-G10-H10 -> 10503.604 | J10: =Premissas!$B$14+Premissas!$B$15 -> 8000 | K10: =I10-J10 -> 2503.6035 | L10: =K10 -> 2503.6035 | M10: =M9+L10 -> -30556.572 | N10: =IF(M10>=0,1,0) -> 0
A11: =A10+1 -> 6 | B11: =MIN(Premissas!$B$10,B10*(1-Premissas!$B$11)+IF(A11=1,Premissas!$B$8,Premissas!$B$9*Premissas!$B$25)) -> 11.415762 | C11: =MAX(0,B11-B10*(1-Premissas!$B$11)) -> 2 | D11: =B11*Premissas!$B$6*Premissas!$B$26 -> 17123.643 | E11: =C11*Premissas!$B$7*Premissas!$B$26 -> 2000 | F11: =D11+E11 -> 19123.643 | G11: =F11*Premissas!$B$13 -> 1147.4186 | H11: =F11*Premissas!$B$12 -> 5737.0929 | I11: =F11-G11-H11 -> 12239.131 | J11: =Premissas!$B$14+Premissas!$B$15 -> 8000 | K11: =I11-J11 -> 4239.1314 | L11: =K11 -> 4239.1314 | M11: =M10+L11 -> -26317.44 | N11: =IF(M11>=0,1,0) -> 0
A12: =A11+1 -> 7 | B12: =MIN(Premissas!$B$10,B11*(1-Premissas!$B$11)+IF(A12=1,Premissas!$B$8,Premissas!$B$9*Premissas!$B$25)) -> 13.187447 | C12: =MAX(0,B12-B11*(1-Premissas!$B$11)) -> 2 | D12: =B12*Premissas!$B$6*Premissas!$B$26 -> 19781.17 | E12: =C12*Premissas!$B$7*Premissas!$B$26 -> 2000 | F12: =D12+E12 -> 21781.17 | G12: =F12*Premissas!$B$13 -> 1306.8702 | H12: =F12*Premissas!$B$12 -> 6534.351 | I12: =F12-G12-H12 -> 13939.949 | J12: =Premissas!$B$14+Premissas!$B$15 -> 8000 | K12: =I12-J12 -> 5939.9488 | L12: =K12 -> 5939.9488 | M12: =M11+L12 -> -20377.492 | N12: =IF(M12>=0,1,0) -> 0
A13: =A12+1 -> 8 | B13: =MIN(Premissas!$B$10,B12*(1-Premissas!$B$11)+IF(A13=1,Premissas!$B$8,Premissas!$B$9*Premissas!$B$25)) -> 14.923698 | C13: =MAX(0,B13-B12*(1-Premissas!$B$11)) -> 2 | D13: =B13*Premissas!$B$6*Premissas!$B$26 -> 22385.547 | E13: =C13*Premissas!$B$7*Premissas!$B$26 -> 2000 | F13: =D13+E13 -> 24385.547 | G13: =F13*Premissas!$B$13 -> 1463.1328 | H13: =F13*Premissas!$B$12 -> 7315.664 | I13: =F13-G13-H13 -> 15606.75 | J13: =Premissas!$B$14+Premissas!$B$15 -> 8000 | K13: =I13-J13 -> 7606.7498 | L13: =K13 -> 7606.7498 | M13: =M12+L13 -> -12770.742 | N13: =IF(M13>=0,1,0) -> 0
A14: =A13+1 -> 9 | B14: =MIN(Premissas!$B$10,B13*(1-Premissas!$B$11)+IF(A14=1,Premissas!$B$8,Premissas!$B$9*Premissas!$B$25)) -> 16.625224 | C14: =MAX(0,B14-B13*(1-Premissas!$B$11)) -> 2 | D14: =B14*Premissas!$B$6*Premissas!$B$26 -> 24937.836 | E14: =C14*Premissas!$B$7*Premissas!$B$26 -> 2000 | F14: =D14+E14 -> 26937.836 | G14: =F14*Premissas!$B$13 -> 1616.2701 | H14: =F14*Premissas!$B$12 -> 8081.3507 | I14: =F14-G14-H14 -> 17240.215 | J14: =Premissas!$B$14+Premissas!$B$15 -> 8000 | K14: =I14-J14 -> 9240.2148 | L14: =K14 -> 9240.2148 | M14: =M13+L14 -> -3530.5269 | N14: =IF(M14>=0,1,0) -> 0
A15: =A14+1 -> 10 | B15: =MIN(Premissas!$B$10,B14*(1-Premissas!$B$11)+IF(A15=1,Premissas!$B$8,Premissas!$B$9*Premissas!$B$25)) -> 18.292719 | C15: =MAX(0,B15-B14*(1-Premissas!$B$11)) -> 2 | D15: =B15*Premissas!$B$6*Premissas!$B$26 -> 27439.079 | E15: =C15*Premissas!$B$7*Premissas!$B$26 -> 2000 | F15: =D15+E15 -> 29439.079 | G15: =F15*Premissas!$B$13 -> 1766.3447 | H15: =F15*Premissas!$B$12 -> 8831.7237 | I15: =F15-G15-H15 -> 18841.011 | J15: =Premissas!$B$14+Premissas!$B$15 -> 8000 | K15: =I15-J15 -> 10841.011 | L15: =K15 -> 10841.011 | M15: =M14+L15 -> 7310.4836 | N15: =IF(M15>=0,1,0) -> 1
A16: =A15+1 -> 11 | B16: =MIN(Premissas!$B$10,B15*(1-Premissas!$B$11)+IF(A16=1,Premissas!$B$8,Premissas!$B$9*Premissas!$B$25)) -> 19.926865 | C16: =MAX(0,B16-B15*(1-Premissas!$B$11)) -> 2 | D16: =B16*Premissas!$B$6*Premissas!$B$26 -> 29890.297 | E16: =C16*Premissas!$B$7*Premissas!$B$26 -> 2000 | F16: =D16+E16 -> 31890.297 | G16: =F16*Premissas!$B$13 -> 1913.4178 | H16: =F16*Premissas!$B$12 -> 9567.0892 | I16: =F16-G16-H16 -> 20409.79 | J16: =Premissas!$B$14+Premissas!$B$15 -> 8000 | K16: =I16-J16 -> 12409.79 | L16: =K16 -> 12409.79 | M16: =M15+L16 -> 19720.274 | N16: =IF(M16>=0,1,0) -> 1
A17: =A16+1 -> 12 | B17: =MIN(Premissas!$B$10,B16*(1-Premissas!$B$11)+IF(A17=1,Premissas!$B$8,Premissas!$B$9*Premissas!$B$25)) -> 21.528328 | C17: =MAX(0,B17-B16*(1-Premissas!$B$11)) -> 2 | D17: =B17*Premissas!$B$6*Premissas!$B$26 -> 32292.491 | E17: =C17*Premissas!$B$7*Premissas!$B$26 -> 2000 | F17: =D17+E17 -> 34292.491 | G17: =F17*Premissas!$B$13 -> 2057.5495 | H17: =F17*Premissas!$B$12 -> 10287.747 | I17: =F17-G17-H17 -> 21947.195 | J17: =Premissas!$B$14+Premissas!$B$15 -> 8000 | K17: =I17-J17 -> 13947.195 | L17: =K17 -> 13947.195 | M17: =M16+L17 -> 33667.468 | N17: =IF(M17>=0,1,0) -> 1
... A41: =A40+1 -> 36 | B41: =MIN(Premissas!$B$10,B40*(1-Premissas!$B$11)+IF(A41=1,Premissas!$B$8,Premissas!$B$9*Premissas!$B$25)) -> 40 | C41: =MAX(0,B41-B40*(1-Premissas!$B$11)) -> 0.8 | D41: =B41*Premissas!$B$6*Premissas!$B$26 -> 60000 | E41: =C41*Premissas!$B$7*Premissas!$B$26 -> 800 | F41: =D41+E41 -> 60800 | G41: =F41*Premissas!$B$13 -> 3648 | H41: =F41*Premissas!$B$12 -> 18240 | I41: =F41-G41-H41 -> 38912 | J41: =Premissas!$B$14+Premissas!$B$15 -> 8000 | K41: =I41-J41 -> 30912 | L41: =K41 -> 30912 | M41: =M40+L41 -> 681947.4 | N41: =IF(M41>=0,1,0) -> 1
A43: Linhas cinza = fim de cada ano (meses 12, 24 e 36).

Sheet Fluxo NR-1
A1: Fluxo mensal - Consultoria NR-1
A2: Cenário ativo: | B2: =Premissas!$B$18 -> Base
A4: Mês | B4: Clientes ativos | C4: Novos clientes (efetivos) | D4: Receita recorrente | E4: Receita de implantação | F4: Receita total | G4: Impostos | H4: Custos variáveis | I4: Margem de contribuição | J4: Custos fixos + pró-labore | K4: Resultado operacional | L4: Fluxo de caixa | M4: Caixa acumulado | N4: Payback atingido? (1=sim)
A5: 0 | B5: 0 | C5: 0 | D5: 0 | E5: 0 | F5: 0 | G5: 0 | H5: 0 | I5: 0 | J5: 0 | K5: 0 | L5: =-Premissas!$C$5 -> -40000 | M5: =L5 -> -40000 | N5: =IF(M5>=0,1,0) -> 0
A6: =A5+1 -> 1 | B6: =MIN(Premissas!$C$10,B5*(1-Premissas!$C$11)+IF(A6=1,Premissas!$C$8,Premissas!$C$9*Premissas!$B$25)) -> 1 | C6: =MAX(0,B6-B5*(1-Premissas!$C$11)) -> 1 | D6: =B6*Premissas!$C$6*Premissas!$B$26 -> 1200 | E6: =C6*Premissas!$C$7*Premissas!$B$26 -> 8000 | F6: =D6+E6 -> 9200 | G6: =F6*Premissas!$C$13 -> 552 | H6: =F6*Premissas!$C$12 -> 3220 | I6: =F6-G6-H6 -> 5428 | J6: =Premissas!$C$14+Premissas!$C$15 -> 10000 | K6: =I6-J6 -> -4572 | L6: =K6 -> -4572 | M6: =M5+L6 -> -44572 | N6: =IF(M6>=0,1,0) -> 0
A7: =A6+1 -> 2 | B7: =MIN(Premissas!$C$10,B6*(1-Premissas!$C$11)+IF(A7=1,Premissas!$C$8,Premissas!$C$9*Premissas!$B$25)) -> 2.47 | C7: =MAX(0,B7-B6*(1-Premissas!$C$11)) -> 1.5 | D7: =B7*Premissas!$C$6*Premissas!$B$26 -> 2964 | E7: =C7*Premissas!$C$7*Premissas!$B$26 -> 12000 | F7: =D7+E7 -> 14964 | G7: =F7*Premissas!$C$13 -> 897.84 | H7: =F7*Premissas!$C$12 -> 5237.4 | I7: =F7-G7-H7 -> 8828.76 | J7: =Premissas!$C$14+Premissas!$C$15 -> 10000 | K7: =I7-J7 -> -1171.24 | L7: =K7 -> -1171.24 | M7: =M6+L7 -> -45743.24 | N7: =IF(M7>=0,1,0) -> 0
A8: =A7+1 -> 3 | B8: =MIN(Premissas!$C$10,B7*(1-Premissas!$C$11)+IF(A8=1,Premissas!$C$8,Premissas!$C$9*Premissas!$B$25)) -> 3.8959 | C8: =MAX(0,B8-B7*(1-Premissas!$C$11)) -> 1.5 | D8: =B8*Premissas!$C$6*Premissas!$B$26 -> 4675.08 | E8: =C8*Premissas!$C$7*Premissas!$B$26 -> 12000 | F8: =D8+E8 -> 16675.08 | G8: =F8*Premissas!$C$13 -> 1000.5048 | H8: =F8*Premissas!$C$12 -> 5836.278 | I8: =F8-G8-H8 -> 9838.2972 | J8: =Premissas!$C$14+Premissas!$C$15 -> 10000 | K8: =I8-J8 -> -161.7028 | L8: =K8 -> -161.7028 | M8: =M7+L8 -> -45904.943 | N8: =IF(M8>=0,1,0) -> 0
A9: =A8+1 -> 4 | B9: =MIN(Premissas!$C$10,B8*(1-Premissas!$C$11)+IF(A9=1,Premissas!$C$8,Premissas!$C$9*Premissas!$B$25)) -> 5.279023 | C9: =MAX(0,B9-B8*(1-Premissas!$C$11)) -> 1.5 | D9: =B9*Premissas!$C$6*Premissas!$B$26 -> 6334.8276 | E9: =C9*Premissas!$C$7*Premissas!$B$26 -> 12000 | F9: =D9+E9 -> 18334.828 | G9: =F9*Premissas!$C$13 -> 1100.0897 | H9: =F9*Premissas!$C$12 -> 6417.1897 | I9: =F9-G9-H9 -> 10817.548 | J9: =Premissas!$C$14+Premissas!$C$15 -> 10000 | K9: =I9-J9 -> 817.54828 | L9: =K9 -> 817.54828 | M9: =M8+L9 -> -45087.395 | N9: =IF(M9>=0,1,0) -> 0
A10: =A9+1 -> 5 | B10: =MIN(Premissas!$C$10,B9*(1-Premissas!$C$11)+IF(A10=1,Premissas!$C$8,Premissas!$C$9*Premissas!$B$25)) -> 6.6206523 | C10: =MAX(0,B10-B9*(1-Premissas!$C$11)) -> 1.5 | D10: =B10*Premissas!$C$6*Premissas!$B$26 -> 7944.7828 | E10: =C10*Premissas!$C$7*Premissas!$B$26 -> 12000 | F10: =D10+E10 -> 19944.783 | G10: =F10*Premissas!$C$13 -> 1196.687 | H10: =F10*Premissas!$C$12 -> 6980.674 | I10: =F10-G10-H10 -> 11767.422 | J10: =Premissas!$C$14+Premissas!$C$15 -> 10000 | K10: =I10-J10 -> 1767.4218 | L10: =K10 -> 1767.4218 | M10: =M9+L10 -> -43319.973 | N10: =IF(M10>=0,1,0) -> 0
A11: =A10+1 -> 6 | B11: =MIN(Premissas!$C$10,B10*(1-Premissas!$C$11)+IF(A11=1,Premissas!$C$8,Premissas!$C$9*Premissas!$B$25)) -> 7.9220327 | C11: =MAX(0,B11-B10*(1-Premissas!$C$11)) -> 1.5 | D11: =B11*Premissas!$C$6*Premissas!$B$26 -> 9506.4393 | E11: =C11*Premissas!$C$7*Premissas!$B$26 -> 12000 | F11: =D11+E11 -> 21506.439 | G11: =F11*Premissas!$C$13 -> 1290.3864 | H11: =F11*Premissas!$C$12 -> 7527.2538 | I11: =F11-G11-H11 -> 12688.799 | J11: =Premissas!$C$14+Premissas!$C$15 -> 10000 | K11: =I11-J11 -> 2688.7992 | L11: =K11 -> 2688.7992 | M11: =M10+L11 -> -40631.174 | N11: =IF(M11>=0,1,0) -> 0
A12: =A11+1 -> 7 | B12: =MIN(Premissas!$C$10,B11*(1-Premissas!$C$11)+IF(A12=1,Premissas!$C$8,Premissas!$C$9*Premissas!$B$25)) -> 9.1843718 | C12: =MAX(0,B12-B11*(1-Premissas!$C$11)) -> 1.5 | D12: =B12*Premissas!$C$6*Premissas!$B$26 -> 11021.246 | E12: =C12*Premissas!$C$7*Premissas!$B$26 -> 12000 | F12: =D12+E12 -> 23021.246 | G12: =F12*Premissas!$C$13 -> 1381.2748 | H12: =F12*Premissas!$C$12 -> 8057.4361 | I12: =F12-G12-H12 -> 13582.535 | J12: =Premissas!$C$14+Premissas!$C$15 -> 10000 | K12: =I12-J12 -> 3582.5352 | L12: =K12 -> 3582.5352 | M12: =M11+L12 -> -37048.638 | N12: =IF(M12>=0,1,0) -> 0
A13: =A12+1 -> 8 | B13: =MIN(Premissas!$C$10,B12*(1-Premissas!$C$11)+IF(A13=1,Premissas!$C$8,Premissas!$C$9*Premissas!$B$25)) -> 10.408841 | C13: =MAX(0,B13-B12*(1-Premissas!$C$11)) -> 1.5 | D13: =B13*Premissas!$C$6*Premissas!$B$26 -> 12490.609 | E13: =C13*Premissas!$C$7*Premissas!$B$26 -> 12000 | F13: =D13+E13 -> 24490.609 | G13: =F13*Premissas!$C$13 -> 1469.4365 | H13: =F13*Premissas!$C$12 -> 8571.7131 | I13: =F13-G13-H13 -> 14449.459 | J13: =Premissas!$C$14+Premissas!$C$15 -> 10000 | K13: =I13-J13 -> 4449.4591 | L13: =K13 -> 4449.4591 | M13: =M12+L13 -> -32599.179 | N13: =IF(M13>=0,1,0) -> 0
A14: =A13+1 -> 9 | B14: =MIN(Premissas!$C$10,B13*(1-Premissas!$C$11)+IF(A14=1,Premissas!$C$8,Premissas!$C$9*Premissas!$B$25)) -> 11.596575 | C14: =MAX(0,B14-B13*(1-Premissas!$C$11)) -> 1.5 | D14: =B14*Premissas!$C$6*Premissas!$B$26 -> 13915.89 | E14: =C14*Premissas!$C$7*Premissas!$B$26 -> 12000 | F14: =D14+E14 -> 25915.89 | G14: =F14*Premissas!$C$13 -> 1554.9534 | H14: =F14*Premissas!$C$12 -> 9070.5617 | I14: =F14-G14-H14 -> 15290.375 | J14: =Premissas!$C$14+Premissas!$C$15 -> 10000 | K14: =I14-J14 -> 5290.3754 | L14: =K14 -> 5290.3754 | M14: =M13+L14 -> -27308.804 | N14: =IF(M14>=0,1,0) -> 0
A15: =A14+1 -> 10 | B15: =MIN(Premissas!$C$10,B14*(1-Premissas!$C$11)+IF(A15=1,Premissas!$C$8,Premissas!$C$9*Premissas!$B$25)) -> 12.748678 | C15: =MAX(0,B15-B14*(1-Premissas!$C$11)) -> 1.5 | D15: =B15*Premissas!$C$6*Premissas!$B$26 -> 15298.414 | E15: =C15*Premissas!$C$7*Premissas!$B$26 -> 12000 | F15: =D15+E15 -> 27298.414 | G15: =F15*Premissas!$C$13 -> 1637.9048 | H15: =F15*Premissas!$C$12 -> 9554.4448 | I15: =F15-G15-H15 -> 16106.064 | J15: =Premissas!$C$14+Premissas!$C$15 -> 10000 | K15: =I15-J15 -> 6106.0641 | L15: =K15 -> 6106.0641 | M15: =M14+L15 -> -21202.74 | N15: =IF(M15>=0,1,0) -> 0
A16: =A15+1 -> 11 | B16: =MIN(Premissas!$C$10,B15*(1-Premissas!$C$11)+IF(A16=1,Premissas!$C$8,Premissas!$C$9*Premissas!$B$25)) -> 13.866218 | C16: =MAX(0,B16-B15*(1-Premissas!$C$11)) -> 1.5 | D16: =B16*Premissas!$C$6*Premissas!$B$26 -> 16639.461 | E16: =C16*Premissas!$C$7*Premissas!$B$26 -> 12000 | F16: =D16+E16 -> 28639.461 | G16: =F16*Premissas!$C$13 -> 1718.3677 | H16: =F16*Premissas!$C$12 -> 10023.811 | I16: =F16-G16-H16 -> 16897.282 | J16: =Premissas!$C$14+Premissas!$C$15 -> 10000 | K16: =I16-J16 -> 6897.2822 | L16: =K16 -> 6897.2822 | M16: =M15+L16 -> -14305.457 | N16: =IF(M16>=0,1,0) -> 0
A17: =A16+1 -> 12 | B17: =MIN(Premissas!$C$10,B16*(1-Premissas!$C$11)+IF(A17=1,Premissas!$C$8,Premissas!$C$9*Premissas!$B$25)) -> 14.950231 | C17: =MAX(0,B17-B16*(1-Premissas!$C$11)) -> 1.5 | D17: =B17*Premissas!$C$6*Premissas!$B$26 -> 17940.277 | E17: =C17*Premissas!$C$7*Premissas!$B$26 -> 12000 | F17: =D17+E17 -> 29940.277 | G17: =F17*Premissas!$C$13 -> 1796.4166 | H17: =F17*Premissas!$C$12 -> 10479.097 | I17: =F17-G17-H17 -> 17664.764 | J17: =Premissas!$C$14+Premissas!$C$15 -> 10000 | K17: =I17-J17 -> 7664.7637 | L17: =K17 -> 7664.7637 | M17: =M16+L17 -> -6640.6937 | N17: =IF(M17>=0,1,0) -> 0
... A41: =A40+1 -> 36 | B41: =MIN(Premissas!$C$10,B40*(1-Premissas!$C$11)+IF(A41=1,Premissas!$C$8,Premissas!$C$9*Premissas!$B$25)) -> 30 | C41: =MAX(0,B41-B40*(1-Premissas!$C$11)) -> 0.9 | D41: =B41*Premissas!$C$6*Premissas!$B$26 -> 36000 | E41: =C41*Premissas!$C$7*Premissas!$B$26 -> 7200 | F41: =D41+E41 -> 43200 | G41: =F41*Premissas!$C$13 -> 2592 | H41: =F41*Premissas!$C$12 -> 15120 | I41: =F41-G41-H41 -> 25488 | J41: =Premissas!$C$14+Premissas!$C$15 -> 10000 | K41: =I41-J41 -> 15488 | L41: =K41 -> 15488 | M41: =M40+L41 -> 333469.49 | N41: =IF(M41>=0,1,0) -> 1
A43: Linhas cinza = fim de cada ano (meses 12, 24 e 36).

Sheet Fluxo Cuidadores
A1: Fluxo mensal - Agência de cuidadores
A2: Cenário ativo: | B2: =Premissas!$B$18 -> Base
A4: Mês | B4: Clientes ativos | C4: Novos clientes (efetivos) | D4: Receita recorrente | E4: Receita de implantação | F4: Receita total | G4: Impostos | H4: Custos variáveis | I4: Margem de contribuição | J4: Custos fixos + pró-labore | K4: Resultado operacional | L4: Fluxo de caixa | M4: Caixa acumulado | N4: Payback atingido? (1=sim)
A5: 0 | B5: 0 | C5: 0 | D5: 0 | E5: 0 | F5: 0 | G5: 0 | H5: 0 | I5: 0 | J5: 0 | K5: 0 | L5: =-Premissas!$D$5 -> -50000 | M5: =L5 -> -50000 | N5: =IF(M5>=0,1,0) -> 0
A6: =A5+1 -> 1 | B6: =MIN(Premissas!$D$10,B5*(1-Premissas!$D$11)+IF(A6=1,Premissas!$D$8,Premissas!$D$9*Premissas!$B$25)) -> 2 | C6: =MAX(0,B6-B5*(1-Premissas!$D$11)) -> 2 | D6: =B6*Premissas!$D$6*Premissas!$B$26 -> 11000 | E6: =C6*Premissas!$D$7*Premissas!$B$26 -> 0 | F6: =D6+E6 -> 11000 | G6: =F6*Premissas!$D$13 -> 1210 | H6: =F6*Premissas!$D$12 -> 8580 | I6: =F6-G6-H6 -> 1210 | J6: =Premissas!$D$14+Premissas!$D$15 -> 11000 | K6: =I6-J6 -> -9790 | L6: =K6 -> -9790 | M6: =M5+L6 -> -59790 | N6: =IF(M6>=0,1,0) -> 0
A7: =A6+1 -> 2 | B7: =MIN(Premissas!$D$10,B6*(1-Premissas!$D$11)+IF(A7=1,Premissas!$D$8,Premissas!$D$9*Premissas!$B$25)) -> 3.4 | C7: =MAX(0,B7-B6*(1-Premissas!$D$11)) -> 1.5 | D7: =B7*Premissas!$D$6*Premissas!$B$26 -> 18700 | E7: =C7*Premissas!$D$7*Premissas!$B$26 -> 0 | F7: =D7+E7 -> 18700 | G7: =F7*Premissas!$D$13 -> 2057 | H7: =F7*Premissas!$D$12 -> 14586 | I7: =F7-G7-H7 -> 2057 | J7: =Premissas!$D$14+Premissas!$D$15 -> 11000 | K7: =I7-J7 -> -8943 | L7: =K7 -> -8943 | M7: =M6+L7 -> -68733 | N7: =IF(M7>=0,1,0) -> 0
A8: =A7+1 -> 3 | B8: =MIN(Premissas!$D$10,B7*(1-Premissas!$D$11)+IF(A8=1,Premissas!$D$8,Premissas!$D$9*Premissas!$B$25)) -> 4.73 | C8: =MAX(0,B8-B7*(1-Premissas!$D$11)) -> 1.5 | D8: =B8*Premissas!$D$6*Premissas!$B$26 -> 26015 | E8: =C8*Premissas!$D$7*Premissas!$B$26 -> 0 | F8: =D8+E8 -> 26015 | G8: =F8*Premissas!$D$13 -> 2861.65 | H8: =F8*Premissas!$D$12 -> 20291.7 | I8: =F8-G8-H8 -> 2861.65 | J8: =Premissas!$D$14+Premissas!$D$15 -> 11000 | K8: =I8-J8 -> -8138.35 | L8: =K8 -> -8138.35 | M8: =M7+L8 -> -76871.35 | N8: =IF(M8>=0,1,0) -> 0
A9: =A8+1 -> 4 | B9: =MIN(Premissas!$D$10,B8*(1-Premissas!$D$11)+IF(A9=1,Premissas!$D$8,Premissas!$D$9*Premissas!$B$25)) -> 5.9935 | C9: =MAX(0,B9-B8*(1-Premissas!$D$11)) -> 1.5 | D9: =B9*Premissas!$D$6*Premissas!$B$26 -> 32964.25 | E9: =C9*Premissas!$D$7*Premissas!$B$26 -> 0 | F9: =D9+E9 -> 32964.25 | G9: =F9*Premissas!$D$13 -> 3626.0675 | H9: =F9*Premissas!$D$12 -> 25712.115 | I9: =F9-G9-H9 -> 3626.0675 | J9: =Premissas!$D$14+Premissas!$D$15 -> 11000 | K9: =I9-J9 -> -7373.9325 | L9: =K9 -> -7373.9325 | M9: =M8+L9 -> -84245.283 | N9: =IF(M9>=0,1,0) -> 0
A10: =A9+1 -> 5 | B10: =MIN(Premissas!$D$10,B9*(1-Premissas!$D$11)+IF(A10=1,Premissas!$D$8,Premissas!$D$9*Premissas!$B$25)) -> 7.193825 | C10: =MAX(0,B10-B9*(1-Premissas!$D$11)) -> 1.5 | D10: =B10*Premissas!$D$6*Premissas!$B$26 -> 39566.037 | E10: =C10*Premissas!$D$7*Premissas!$B$26 -> 0 | F10: =D10+E10 -> 39566.037 | G10: =F10*Premissas!$D$13 -> 4352.2641 | H10: =F10*Premissas!$D$12 -> 30861.509 | I10: =F10-G10-H10 -> 4352.2641 | J10: =Premissas!$D$14+Premissas!$D$15 -> 11000 | K10: =I10-J10 -> -6647.7359 | L10: =K10 -> -6647.7359 | M10: =M9+L10 -> -90893.018 | N10: =IF(M10>=0,1,0) -> 0
A11: =A10+1 -> 6 | B11: =MIN(Premissas!$D$10,B10*(1-Premissas!$D$11)+IF(A11=1,Premissas!$D$8,Premissas!$D$9*Premissas!$B$25)) -> 8.3341337 | C11: =MAX(0,B11-B10*(1-Premissas!$D$11)) -> 1.5 | D11: =B11*Premissas!$D$6*Premissas!$B$26 -> 45837.736 | E11: =C11*Premissas!$D$7*Premissas!$B$26 -> 0 | F11: =D11+E11 -> 45837.736 | G11: =F11*Premissas!$D$13 -> 5042.1509 | H11: =F11*Premissas!$D$12 -> 35753.434 | I11: =F11-G11-H11 -> 5042.1509 | J11: =Premissas!$D$14+Premissas!$D$15 -> 11000 | K11: =I11-J11 -> -5957.8491 | L11: =K11 -> -5957.8491 | M11: =M10+L11 -> -96850.867 | N11: =IF(M11>=0,1,0) -> 0
A12: =A11+1 -> 7 | B12: =MIN(Premissas!$D$10,B11*(1-Premissas!$D$11)+IF(A12=1,Premissas!$D$8,Premissas!$D$9*Premissas!$B$25)) -> 9.4174271 | C12: =MAX(0,B12-B11*(1-Premissas!$D$11)) -> 1.5 | D12: =B12*Premissas!$D$6*Premissas!$B$26 -> 51795.849 | E12: =C12*Premissas!$D$7*Premissas!$B$26 -> 0 | F12: =D12+E12 -> 51795.849 | G12: =F12*Premissas!$D$13 -> 5697.5434 | H12: =F12*Premissas!$D$12 -> 40400.762 | I12: =F12-G12-H12 -> 5697.5434 | J12: =Premissas!$D$14+Premissas!$D$15 -> 11000 | K12: =I12-J12 -> -5302.4566 | L12: =K12 -> -5302.4566 | M12: =M11+L12 -> -102153.32 | N12: =IF(M12>=0,1,0) -> 0
A13: =A12+1 -> 8 | B13: =MIN(Premissas!$D$10,B12*(1-Premissas!$D$11)+IF(A13=1,Premissas!$D$8,Premissas!$D$9*Premissas!$B$25)) -> 10.446556 | C13: =MAX(0,B13-B12*(1-Premissas!$D$11)) -> 1.5 | D13: =B13*Premissas!$D$6*Premissas!$B$26 -> 57456.056 | E13: =C13*Premissas!$D$7*Premissas!$B$26 -> 0 | F13: =D13+E13 -> 57456.056 | G13: =F13*Premissas!$D$13 -> 6320.1662 | H13: =F13*Premissas!$D$12 -> 44815.724 | I13: =F13-G13-H13 -> 6320.1662 | J13: =Premissas!$D$14+Premissas!$D$15 -> 11000 | K13: =I13-J13 -> -4679.8338 | L13: =K13 -> -4679.8338 | M13: =M12+L13 -> -106833.16 | N13: =IF(M13>=0,1,0) -> 0
A14: =A13+1 -> 9 | B14: =MIN(Premissas!$D$10,B13*(1-Premissas!$D$11)+IF(A14=1,Premissas!$D$8,Premissas!$D$9*Premissas!$B$25)) -> 11.424228 | C14: =MAX(0,B14-B13*(1-Premissas!$D$11)) -> 1.5 | D14: =B14*Premissas!$D$6*Premissas!$B$26 -> 62833.254 | E14: =C14*Premissas!$D$7*Premissas!$B$26 -> 0 | F14: =D14+E14 -> 62833.254 | G14: =F14*Premissas!$D$13 -> 6911.6579 | H14: =F14*Premissas!$D$12 -> 49009.938 | I14: =F14-G14-H14 -> 6911.6579 | J14: =Premissas!$D$14+Premissas!$D$15 -> 11000 | K14: =I14-J14 -> -4088.3421 | L14: =K14 -> -4088.3421 | M14: =M13+L14 -> -110921.5 | N14: =IF(M14>=0,1,0) -> 0
A15: =A14+1 -> 10 | B15: =MIN(Premissas!$D$10,B14*(1-Premissas!$D$11)+IF(A15=1,Premissas!$D$8,Premissas!$D$9*Premissas!$B$25)) -> 12.353017 | C15: =MAX(0,B15-B14*(1-Premissas!$D$11)) -> 1.5 | D15: =B15*Premissas!$D$6*Premissas!$B$26 -> 67941.591 | E15: =C15*Premissas!$D$7*Premissas!$B$26 -> 0 | F15: =D15+E15 -> 67941.591 | G15: =F15*Premissas!$D$13 -> 7473.575 | H15: =F15*Premissas!$D$12 -> 52994.441 | I15: =F15-G15-H15 -> 7473.575 | J15: =Premissas!$D$14+Premissas!$D$15 -> 11000 | K15: =I15-J15 -> -3526.425 | L15: =K15 -> -3526.425 | M15: =M14+L15 -> -114447.92 | N15: =IF(M15>=0,1,0) -> 0
A16: =A15+1 -> 11 | B16: =MIN(Premissas!$D$10,B15*(1-Premissas!$D$11)+IF(A16=1,Premissas!$D$8,Premissas!$D$9*Premissas!$B$25)) -> 13.235366 | C16: =MAX(0,B16-B15*(1-Premissas!$D$11)) -> 1.5 | D16: =B16*Premissas!$D$6*Premissas!$B$26 -> 72794.511 | E16: =C16*Premissas!$D$7*Premissas!$B$26 -> 0 | F16: =D16+E16 -> 72794.511 | G16: =F16*Premissas!$D$13 -> 8007.3962 | H16: =F16*Premissas!$D$12 -> 56779.719 | I16: =F16-G16-H16 -> 8007.3962 | J16: =Premissas!$D$14+Premissas!$D$15 -> 11000 | K16: =I16-J16 -> -2992.6038 | L16: =K16 -> -2992.6038 | M16: =M15+L16 -> -117440.53 | N16: =IF(M16>=0,1,0) -> 0
A17: =A16+1 -> 12 | B17: =MIN(Premissas!$D$10,B16*(1-Premissas!$D$11)+IF(A17=1,Premissas!$D$8,Premissas!$D$9*Premissas!$B$25)) -> 14.073597 | C17: =MAX(0,B17-B16*(1-Premissas!$D$11)) -> 1.5 | D17: =B17*Premissas!$D$6*Premissas!$B$26 -> 77404.786 | E17: =C17*Premissas!$D$7*Premissas!$B$26 -> 0 | F17: =D17+E17 -> 77404.786 | G17: =F17*Premissas!$D$13 -> 8514.5264 | H17: =F17*Premissas!$D$12 -> 60375.733 | I17: =F17-G17-H17 -> 8514.5264 | J17: =Premissas!$D$14+Premissas!$D$15 -> 11000 | K17: =I17-J17 -> -2485.4736 | L17: =K17 -> -2485.4736 | M17: =M16+L17 -> -119926 | N17: =IF(M17>=0,1,0) -> 0
... A41: =A40+1 -> 36 | B41: =MIN(Premissas!$D$10,B40*(1-Premissas!$D$11)+IF(A41=1,Premissas!$D$8,Premissas!$D$9*Premissas!$B$25)) -> 25.349665 | C41: =MAX(0,B41-B40*(1-Premissas!$D$11)) -> 1.5 | D41: =B41*Premissas!$D$6*Premissas!$B$26 -> 139423.16 | E41: =C41*Premissas!$D$7*Premissas!$B$26 -> 0 | F41: =D41+E41 -> 139423.16 | G41: =F41*Premissas!$D$13 -> 15336.547 | H41: =F41*Premissas!$D$12 -> 108750.06 | I41: =F41-G41-H41 -> 15336.547 | J41: =Premissas!$D$14+Premissas!$D$15 -> 11000 | K41: =I41-J41 -> 4336.5475 | L41: =K41 -> 4336.5475 | M41: =M40+L41 -> -77944.402 | N41: =IF(M41>=0,1,0) -> 0
A43: Linhas cinza = fim de cada ano (meses 12, 24 e 36).

Sheet Validação de campo
A1: Validação de campo - concorrentes e cotações no Alto Tietê
A2: Preencha uma linha por concorrente encontrado (Google Maps, indicações, cotação oculta). A linha 5 é um EXEMPLO fictício de formato: substitua pelos seus dados.
K3: Resumo por oportunidade
A4: Oportunidade | B4: Cidade | C4: Empresa | D4: Nota Google | E4: Nº avaliações | F4: Preço cotado (R$) | G4: Prazo para atender (dias) | H4: Pontos fracos / reclamações | I4: Data | K4: Oportunidade | L4: Concorrentes | M4: Nota média | N4: Preço médio (R$) | O4: Prazo médio (dias)
A5: BPO financeiro | B5: Mogi das Cruzes | C5: Exemplo Ltda (fictício) | D5: 4.3 | E5: 27 | F5: 1800 | G5: 10 | H5: Só faz lançamentos, sem relatório gerencial | I5: 2026-10-20 | K5: BPO financeiro | L5: =COUNTIF($A$5:$A$200,K5) -> 1 | M5: =IFERROR(AVERAGEIF($A$5:$A$200,K5,$D$5:$D$200),"-") -> 4.3 | N5: =IFERROR(AVERAGEIF($A$5:$A$200,K5,$F$5:$F$200),"-") -> 1800 | O5: =IFERROR(AVERAGEIF($A$5:$A$200,K5,$G$5:$G$200),"-") -> 10
K6: Consultoria NR-1 | L6: =COUNTIF($A$5:$A$200,K6) -> 0 | M6: =IFERROR(AVERAGEIF($A$5:$A$200,K6,$D$5:$D$200),"-") -> - | N6: =IFERROR(AVERAGEIF($A$5:$A$200,K6,$F$5:$F$200),"-") -> - | O6: =IFERROR(AVERAGEIF($A$5:$A$200,K6,$G$5:$G$200),"-") -> -
K7: Agência de cuidadores | L7: =COUNTIF($A$5:$A$200,K7) -> 0 | M7: =IFERROR(AVERAGEIF($A$5:$A$200,K7,$D$5:$D$200),"-") -> - | N7: =IFERROR(AVERAGEIF($A$5:$A$200,K7,$F$5:$F$200),"-") -> - | O7: =IFERROR(AVERAGEIF($A$5:$A$200,K7,$G$5:$G$200),"-") -> -
K9: Use o preço médio para revisar o ticket na aba Premissas.
